{
  "@context": "http://www.w3.org/ns/anno.jsonld",
  "id": "http://visual-essays.app/annotations/?include=description&target=/87fd9ca3",
  "type": "AnnotationPage",
  "partOf": {
    "id": "http://visual-essays.app/annotations/?include=description&target=/87fd9ca3",
    "total": 4,
    "modified": "2020-12-15T16:35:02.206394"
  },
  "startIndex": 0,
  "items": [
    {
      "type": "Annotation",
      "body": [
        {
          "type": "TextualBody",
          "value": "tower",
          "purpose": "commenting"
        }
      ],
      "target": {
        "selector": {
          "type": "FragmentSelector",
          "conformsTo": "http://www.w3.org/TR/media-frags/",
          "value": "xywh=pixel:3353.226318359375,1534.5882568359375,816.380126953125,874.9393310546875"
        },
        "id": "README/87fd9ca3"
      },
      "@context": "http://www.w3.org/ns/anno.jsonld",
      "id": "README/87fd9ca3/02182574",
      "seq": 0
    },
    {
      "type": "Annotation",
      "body": [
        {
          "type": "TextualBody",
          "value": "Theater marque",
          "purpose": "commenting"
        }
      ],
      "target": {
        "selector": {
          "type": "FragmentSelector",
          "conformsTo": "http://www.w3.org/TR/media-frags/",
          "value": "xywh=pixel:516.6963500976562,2456.030029296875,1583.1576538085938,640.70361328125"
        },
        "id": "README/87fd9ca3"
      },
      "@context": "http://www.w3.org/ns/anno.jsonld",
      "id": "README/87fd9ca3/55b43b3b",
      "seq": 1
    },
    {
      "type": "Annotation",
      "body": [
        {
          "type": "TextualBody",
          "value": "test",
          "purpose": "commenting"
        }
      ],
      "target": {
        "selector": {
          "type": "FragmentSelector",
          "conformsTo": "http://www.w3.org/TR/media-frags/",
          "value": "xywh=pixel:686.087646484375,2553.770751953125,1110.3350830078125,526.994873046875"
        },
        "id": "README/87fd9ca3"
      },
      "@context": "http://www.w3.org/ns/anno.jsonld",
      "id": "README/87fd9ca3/8d93c45b",
      "seq": 0
    },
    {
      "type": "Annotation",
      "body": [
        {
          "type": "TextualBody",
          "value": "clock tower",
          "purpose": "commenting"
        }
      ],
      "target": {
        "selector": {
          "type": "FragmentSelector",
          "conformsTo": "http://www.w3.org/TR/media-frags/",
          "value": "xywh=pixel:3379.12255859375,1562.2540283203125,652.55517578125,865.0150146484375"
        },
        "id": "README/87fd9ca3"
      },
      "@context": "http://www.w3.org/ns/anno.jsonld",
      "id": "README/87fd9ca3/773681b8",
      "seq": 0
    }
  ]
}